robin_chat/__init__.py
robin_chat/frontend/build/asset-manifest.json
robin_chat/frontend/build/bootstrap.min.css
robin_chat/frontend/build/bootstrap.min.css.map
robin_chat/frontend/build/index.html
robin_chat/frontend/build/precache-manifest.e17fb96287d306b6608e233bdf1013d3.js
robin_chat/frontend/build/service-worker.js
robin_chat/frontend/build/static/js/2.ca4fbee2.chunk.js
robin_chat/frontend/build/static/js/2.ca4fbee2.chunk.js.LICENSE.txt
robin_chat/frontend/build/static/js/2.ca4fbee2.chunk.js.map
robin_chat/frontend/build/static/js/main.7edbfefd.chunk.js
robin_chat/frontend/build/static/js/main.7edbfefd.chunk.js.map
robin_chat/frontend/build/static/js/runtime-main.11ec9aca.js
robin_chat/frontend/build/static/js/runtime-main.11ec9aca.js.map
robin_chat-0.0.2.2.dist-info/LICENSE
robin_chat-0.0.2.2.dist-info/METADATA
robin_chat-0.0.2.2.dist-info/WHEEL
robin_chat-0.0.2.2.dist-info/top_level.txt
robin_chat-0.0.2.2.dist-info/RECORD
