Metadata-Version: 2.1
Name: robin-chat
Version: 0.0.2.2
Summary: Streamlit component for rendering RobinAI chat messages
Home-page: https://github.com/chrisdoyleie/robin-chat
Author: Chris Doyle
Author-email: chris@robinai.co.uk
Keywords: chat streamlit streamlit-component
Classifier: Programming Language :: Python :: 3
Classifier: Operating System :: OS Independent
Requires-Python: >=3.8
License-File: LICENSE
Requires-Dist: streamlit (>=0.63)
